downward_ch-0.0.10.data/purelib/downward_ch/.gitattributes
downward_ch-0.0.10.data/purelib/downward_ch/.gitignore
downward_ch-0.0.10.data/purelib/downward_ch/.uncrustify.cfg
downward_ch-0.0.10.data/purelib/downward_ch/CHANGES.md
downward_ch-0.0.10.data/purelib/downward_ch/LICENSE.md
downward_ch-0.0.10.data/purelib/downward_ch/README.md
downward_ch-0.0.10.data/purelib/downward_ch/__init__.py
downward_ch-0.0.10.data/purelib/downward_ch/build.py
downward_ch-0.0.10.data/purelib/downward_ch/build_configs.py
downward_ch-0.0.10.data/purelib/downward_ch/downward_ch.py
downward_ch-0.0.10.data/purelib/downward_ch/fast-downward.py
downward_ch-0.0.10.data/purelib/downward_ch/builds/release/CMakeCache.txt
downward_ch-0.0.10.data/purelib/downward_ch/builds/release/Makefile
downward_ch-0.0.10.data/purelib/downward_ch/builds/release/cmake_install.cmake
downward_ch-0.0.10.data/purelib/downward_ch/builds/release/CMakeFiles/CMakeDirectoryInformation.cmake
downward_ch-0.0.10.data/purelib/downward_ch/builds/release/CMakeFiles/CMakeOutput.log
downward_ch-0.0.10.data/purelib/downward_ch/builds/release/CMakeFiles/Makefile.cmake
downward_ch-0.0.10.data/purelib/downward_ch/builds/release/CMakeFiles/Makefile2
downward_ch-0.0.10.data/purelib/downward_ch/builds/release/CMakeFiles/TargetDirectories.txt
downward_ch-0.0.10.data/purelib/downward_ch/builds/release/CMakeFiles/cmake.check_cache
downward_ch-0.0.10.data/purelib/downward_ch/builds/release/CMakeFiles/feature_tests.bin
downward_ch-0.0.10.data/purelib/downward_ch/builds/release/CMakeFiles/feature_tests.c
downward_ch-0.0.10.data/purelib/downward_ch/builds/release/CMakeFiles/feature_tests.cxx
downward_ch-0.0.10.data/purelib/downward_ch/builds/release/CMakeFiles/progress.marks
downward_ch-0.0.10.data/purelib/downward_ch/builds/release/CMakeFiles/3.10.2/CMakeCCompiler.cmake
downward_ch-0.0.10.data/purelib/downward_ch/builds/release/CMakeFiles/3.10.2/CMakeCXXCompiler.cmake
downward_ch-0.0.10.dist-info/DESCRIPTION.rst
downward_ch-0.0.10.dist-info/METADATA
downward_ch-0.0.10.dist-info/RECORD
downward_ch-0.0.10.dist-info/WHEEL
downward_ch-0.0.10.dist-info/entry_points.txt
downward_ch-0.0.10.dist-info/metadata.json
downward_ch-0.0.10.dist-info/top_level.txt
